GetPlayerCard-0.4.4.dist-info/METADATA
GetPlayerCard-0.4.4.dist-info/WHEEL
GetPlayerCard-0.4.4.dist-info/entry_points.txt
GetPlayerCard-0.4.4.dist-info/licenses/LICENSE
getpc/excel.py
getpc/_core.pyi
getpc/__init__.py
getpc/__main__.py
getpc/_core.pyd
GetPlayerCard-0.4.4.dist-info/RECORD
